LICENSE
MANIFEST.in
README.md
setup.py
templar/__init__.py
templar/exceptions.py
templar/linker.py
templar/markdown.py
templar.egg-info/PKG-INFO
templar.egg-info/SOURCES.txt
templar.egg-info/dependency_links.txt
templar.egg-info/entry_points.txt
templar.egg-info/requires.txt
templar.egg-info/top_level.txt
templar/api/__init__.py
templar/api/config.py
templar/api/publish.py
templar/api/rules/__init__.py
templar/api/rules/compiler_rules.py
templar/api/rules/core.py
templar/api/rules/table_of_contents.py
templar/cli/__init__.py
templar/cli/templar.py