Metadata-Version: 1.1
Name: templar
Version: 2.0.1
Summary: A static templating engine written in Python
Home-page: https://github.com/albert12132/templar
Author: Albert Wu
Author-email: albert12132@gmail.com
License: MIT
Keywords: templating,static template,markdown
Platform: UNKNOWN
Classifier: Development Status :: 5 - Production/Stable
Classifier: Intended Audience :: Developers
Classifier: License :: OSI Approved :: MIT License
Classifier: Programming Language :: Python :: 3
Classifier: Programming Language :: Python :: 3.3
Classifier: Programming Language :: Python :: 3.4
Classifier: Topic :: Text Processing :: Markup :: HTML
